droppablefileinput/__init__.py
droppablefileinput/widgets.py
droppablefileinput/locale/de/LC_MESSAGES/django.po
droppablefileinput/locale/en/LC_MESSAGES/django.po
droppablefileinput/static/droppablefileinput/css/droppable_file_input.css
droppablefileinput/static/droppablefileinput/images/icon.svg
droppablefileinput/static/droppablefileinput/js/droppable_file_input.js
droppablefileinput/templates/widgets/droppable_file_input.html
droppablefileinput-0.1.2.dist-info/METADATA
droppablefileinput-0.1.2.dist-info/WHEEL
droppablefileinput-0.1.2.dist-info/licenses/LICENSE
droppablefileinput-0.1.2.dist-info/RECORD
