Metadata-Version: 2.4
Name: droppablefileinput
Version: 0.1.2
Summary: DroppableFileInput is a custom Django widget that enhances the usability of file input forms by allowing users to drag and drop files. This widget utilizes JavaScript to provide interactive feedback, such as highlighting the drop area when a file is dragged over and displaying file details on the page.
Project-URL: Homepage, https://github.com/krystofbe/droppablefileinput
Project-URL: Repository, https://github.com/krystofbe/droppablefileinput
Project-URL: Issues, https://github.com/krystofbe/droppablefileinput/issues
Author-email: Krystof Beuermann <krystof@blackbox.ms>
License: MIT License
License-File: LICENSE
Keywords: django,drag-and-drop,file,upload,widget
Classifier: Development Status :: 4 - Beta
Classifier: Framework :: Django
Classifier: Framework :: Django :: 4.0
Classifier: Framework :: Django :: 4.1
Classifier: Framework :: Django :: 4.2
Classifier: Framework :: Django :: 5.0
Classifier: Intended Audience :: Developers
Classifier: License :: OSI Approved :: MIT License
Classifier: Programming Language :: Python
Classifier: Programming Language :: Python :: 3
Classifier: Programming Language :: Python :: 3.11
Classifier: Programming Language :: Python :: 3.12
Requires-Python: <4.0,>=3.11
Requires-Dist: django>=4.0
Provides-Extra: dev
Requires-Dist: coverage<8.0.0,>=7.5.3; extra == 'dev'
Requires-Dist: deptry<0.13.0,>=0.12.0; extra == 'dev'
Requires-Dist: pre-commit<4.0.0,>=3.4.0; extra == 'dev'
Requires-Dist: pytest-cov<6.0.0,>=5.0.0; extra == 'dev'
Requires-Dist: pytest-django<5.0.0,>=4.8.0; extra == 'dev'
Requires-Dist: pytest-playwright<0.6.0,>=0.5.0; extra == 'dev'
Requires-Dist: pytest<8.0.0,>=7.2.0; extra == 'dev'
Requires-Dist: ruff<0.5.0,>=0.4.4; extra == 'dev'
Requires-Dist: tox<5.0.0,>=4.11.1; extra == 'dev'
